watchmaker/__init__.py
watchmaker/__main__.py
watchmaker/cli.py
watchmaker/conditions/__init__.py
watchmaker/config/__init__.py
watchmaker/config/status/__init__.py
watchmaker/exceptions/__init__.py
watchmaker/logger/__init__.py
watchmaker/managers/__init__.py
watchmaker/managers/platform_manager.py
watchmaker/managers/worker_manager.py
watchmaker/static/__init__.py
watchmaker/static/config.yaml
watchmaker/static/salt/content/.gitattributes
watchmaker/static/salt/content/.gitignore
watchmaker/static/salt/content/.mergify.yml
watchmaker/static/salt/content/Dockerfile
watchmaker/static/salt/content/Makefile
watchmaker/static/salt/content/README.md
watchmaker/static/salt/content/.github/dependabot.yml
watchmaker/static/salt/content/.github/workflows/lint.yml
watchmaker/static/salt/content/pillar/map.jinja
watchmaker/static/salt/content/pillar/top.sls
watchmaker/static/salt/content/pillar/common/ash-linux/init.sls
watchmaker/static/salt/content/pillar/common/ash-windows/init.sls
watchmaker/static/salt/content/pillar/common/netbanner/init.sls
watchmaker/static/salt/content/pillar/common/scap/elx.sls
watchmaker/static/salt/content/pillar/common/scap/map.jinja
watchmaker/static/salt/content/pillar/common/scap/windows.sls
watchmaker/static/salt/content/pillar/common/winrepo/init.sls
watchmaker/static/salt/content/states/top.sls
watchmaker/static/salt/content/winrepo/winrepo/dotnet_pkg/init.sls
watchmaker/static/salt/content/winrepo/winrepo/emet_pkg/init.sls
watchmaker/static/salt/content/winrepo/winrepo/mcafee_agent_pkg/init.sls
watchmaker/static/salt/content/winrepo/winrepo/nessus_agent_pkg/init.sls
watchmaker/static/salt/content/winrepo/winrepo/netbanner_pkg/init.sls
watchmaker/static/salt/content/winrepo/winrepo/scc_pkg/init.sls
watchmaker/static/salt/content/winrepo/winrepo/splunkforwarder_pkg/init.sls
watchmaker/static/salt/content/winrepo/winrepo/trellix_agent_pkg/init.sls
watchmaker/static/salt/formulas/amazon-inspector-formula/.travis.yml
watchmaker-0.29.4.dist-info/licenses/AUTHORS.md
watchmaker-0.29.4.dist-info/licenses/LICENSE
watchmaker-0.29.4.dist-info/METADATA
watchmaker-0.29.4.dist-info/WHEEL
watchmaker-0.29.4.dist-info/entry_points.txt
watchmaker-0.29.4.dist-info/top_level.txt
watchmaker-0.29.4.dist-info/RECORD
