Metadata-Version: 2.4
Name: watchmaker
Version: 0.29.4
Summary: Applied Configuration Management
Home-page: https://github.com/plus3it/watchmaker
Author: Plus3IT Maintainers of Watchmaker
Author-email: projects@plus3it.com
License: Apache Software License 2.0
Platform: Linux
Platform: Windows
Classifier: Development Status :: 4 - Beta
Classifier: Intended Audience :: Developers
Classifier: Intended Audience :: System Administrators
Classifier: Operating System :: POSIX :: Linux
Classifier: Operating System :: Microsoft :: Windows
Classifier: Programming Language :: Python
Classifier: Programming Language :: Python :: 3
Classifier: Programming Language :: Python :: 3.6
Classifier: Programming Language :: Python :: 3.7
Classifier: Programming Language :: Python :: 3.8
Classifier: Programming Language :: Python :: 3.9
Classifier: Programming Language :: Python :: 3.10
Classifier: Programming Language :: Python :: 3.11
Classifier: Programming Language :: Python :: 3.12
Classifier: Programming Language :: Python :: Implementation :: CPython
Classifier: Programming Language :: Python :: Implementation :: PyPy
Classifier: Topic :: Utilities
License-File: LICENSE
License-File: AUTHORS.md
Requires-Dist: backoff; python_version >= "3.6"
Requires-Dist: click
Requires-Dist: defusedxml; platform_system == "Windows"
Requires-Dist: distro; python_version >= "3.6"
Requires-Dist: importlib_metadata
Requires-Dist: importlib_resources
Requires-Dist: futures; python_version < "3"
Requires-Dist: six
Requires-Dist: pywin32; platform_system == "Windows"
Requires-Dist: PyYAML; python_version >= "3.6"
Requires-Dist: compatibleversion>=0.1.2
Requires-Dist: oschmod>=0.1.3
Dynamic: license-file
